__init__.py
main.py
sim_modem_cli-1.0.2.dist-info/LICENSE
sim_modem_cli-1.0.2.dist-info/METADATA
sim_modem_cli-1.0.2.dist-info/WHEEL
sim_modem_cli-1.0.2.dist-info/entry_points.txt
sim_modem_cli-1.0.2.dist-info/top_level.txt
sim_modem_cli-1.0.2.dist-info/RECORD
