Metadata-Version: 2.1
Name: sim-modem-cli
Version: 1.0.2
Summary: Easy CLI for interfacing with mobile modems
License: MIT
Project-URL: Repository, https://github.com/jonamat/sim-modem-cli
Keywords: modem,sms,gsm,sim,atcommands
Requires-Python: >=3.7
License-File: LICENSE
Requires-Dist: typer (==0.7.0)
Requires-Dist: sim-modem (==1.0.3)
